Workbook

Sheet ChartData
A1: Month | B1: Revenue | C1: Orders | E1: Category | F1: Revenue | H1: Region | I1: Revenue | K1: Quarter | L1: Revenue | N1: Channel | O1: Revenue
A2: Jan | B2: 3850000 | C2: 128 | E2: Electronics | F2: 38200000 | H2: South | I2: 24800000 | K2: Q1 | L2: 13170000 | N2: Online | O2: 42500000
A3: Feb | B3: 4120000 | C3: 143 | E3: Fashion | F3: 14500000 | H3: North | I3: 18500000 | K3: Q2 | L3: 16640000 | N3: Retail Store | O3: 22800000
A4: Mar | B4: 5200000 | C4: 173 | E4: Home & Kitchen | F4: 9800000 | H4: West | I4: 16200000 | K4: Q3 | L4: 19450000 | N4: Wholesale | O4: 9200000
A5: Apr | B5: 4650000 | C5: 155 | E5: Sports | F5: 6200000 | H5: East | I5: 12300000 | K5: Q4 | L5: 25300000
A6: May | B6: 5890000 | C6: 196 | E6: Books | F6: 3100000 | H6: Central | I6: 2700000
A7: Jun | B7: 6100000 | C7: 203 | E7: Beauty | F7: 2700000
A8: Jul | B8: 5750000 | C8: 191
A9: Aug | B9: 6500000 | C9: 217
A10: Sep | B10: 7200000 | C10: 240
A11: Oct | B11: 6800000 | C11: 227
A12: Nov | B12: 8100000 | C12: 270
A13: Dec | B13: 9400000 | C13: 313

Sheet 📈 Dashboard
A2: ⚡ SHOPNEXUS · WEEK 4 BUSINESS CASE STUDY DASHBOARD · END-TO-END DATA ANALYTICS · FY 2024
B5: 🔽 INTERACTIVE FILTERS — Use AutoFilter dropdowns (▼) on column headers in each data sheet to slice by Region · Quarter · Category · Channel · Month
B8: GROSS REVENUE | H8: NET REVENUE | N8: TOTAL ORDERS | T8: TOP CATEGORY | Z8: BEST REGION
B9: =SUM('🛒 E-Commerce Dataset'!L:L) -> 10722600 | H9: =SUM('🛒 E-Commerce Dataset'!N:N) -> 9742260 | N9: =COUNTA('🛒 E-Commerce Dataset'!A3:A62) -> 60 | T9: =INDEX('🏆 Product Analysis'!A5:A10,MATCH(MIN('🏆 Product Analysis'!H5:H10),'🏆 Product Analysis'!H5:H10,0)) -> Electronics | Z9: =INDEX('🌍 Regional Analysis'!A5:A9,MATCH(MIN('🌍 Regional Analysis'!H5:H9),'🌍 Regional Analysis'!H5:H9,0)) -> South
B12: FY 2024 · All Categories | H12: After All Discounts | N12: 60 Transactions | T12: Business Q1 Answer | Z12: Business Q2 Answer
B15: ● REVENUE TRENDS · Monthly Growth & Quarterly Performance
B38: ● PRODUCT & CHANNEL · Business Q1 — Which Category Sells Most?
B61: ● REGIONAL PERFORMANCE · Business Q2 — Which Region Performs Best?
A82: © 2024 ShopNexus Analytics · Week 4: End-to-End Business Case Study · Mohammed Afroz · All figures in INR

Sheet 🛒 E-Commerce Dataset
A1: SHOPNEXUS · E-COMMERCE SALES TRANSACTION DATABASE · FY 2024
A2: Order ID | B2: Date | C2: Month | D2: Quarter | E2: Customer ID | F2: Region | G2: Channel | H2: Category | I2: Product | J2: Units | K2: Unit Price (₹) | L2: Revenue (₹) | M2: Discount % | N2: Net Revenue (₹)
A3: ORD-001 | B3: 2024-01-03 | C3: January | D3: Q1 | E3: CUST-201 | F3: South | G3: Online | H3: Electronics | I3: Laptop | J3: 2 | K3: 58000 | L3: =J3*K3 -> 116000 | M3: 5 | N3: =L3*(1-M3/100) -> 110200
A4: ORD-002 | B4: 2024-01-07 | C4: January | D4: Q1 | E4: CUST-342 | F4: North | G4: Retail Store | H4: Fashion | I4: Running Shoes | J4: 5 | K4: 4500 | L4: =J4*K4 -> 22500 | M4: 10 | N4: =L4*(1-M4/100) -> 20250
A5: ORD-003 | B5: 2024-01-12 | C5: January | D5: Q1 | E5: CUST-115 | F5: East | G5: Online | H5: Home & Kitchen | I5: Air Fryer | J5: 3 | K5: 8500 | L5: =J5*K5 -> 25500 | M5: 8 | N5: =L5*(1-M5/100) -> 23460
A6: ORD-004 | B6: 2024-01-18 | C6: January | D6: Q1 | E6: CUST-456 | F6: West | G6: Online | H6: Electronics | I6: Smartphone | J6: 4 | K6: 22000 | L6: =J6*K6 -> 88000 | M6: 5 | N6: =L6*(1-M6/100) -> 83600
A7: ORD-005 | B7: 2024-01-25 | C7: January | D7: Q1 | E7: CUST-789 | F7: South | G7: Wholesale | H7: Sports | I7: Yoga Mat | J7: 20 | K7: 1200 | L7: =J7*K7 -> 24000 | M7: 15 | N7: =L7*(1-M7/100) -> 20400
A8: ORD-006 | B8: 2024-02-02 | C8: February | D8: Q1 | E8: CUST-234 | F8: North | G8: Online | H8: Beauty | I8: Skincare Kit | J8: 8 | K8: 3500 | L8: =J8*K8 -> 28000 | M8: 12 | N8: =L8*(1-M8/100) -> 24640
A9: ORD-007 | B9: 2024-02-08 | C9: February | D9: Q1 | E9: CUST-567 | F9: Central | G9: Retail Store | H9: Books | I9: Business Strategy | J9: 15 | K9: 650 | L9: =J9*K9 -> 9750 | M9: 0 | N9: =L9*(1-M9/100) -> 9750
A10: ORD-008 | B10: 2024-02-14 | C10: February | D10: Q1 | E10: CUST-890 | F10: East | G10: Online | H10: Fashion | I10: Ethnic Wear | J10: 6 | K10: 2800 | L10: =J10*K10 -> 16800 | M10: 20 | N10: =L10*(1-M10/100) -> 13440
A11: ORD-009 | B11: 2024-02-20 | C11: February | D11: Q1 | E11: CUST-123 | F11: South | G11: Online | H11: Electronics | I11: Smart Watch | J11: 10 | K11: 18000 | L11: =J11*K11 -> 180000 | M11: 5 | N11: =L11*(1-M11/100) -> 171000
A12: ORD-010 | B12: 2024-02-27 | C12: February | D12: Q1 | E12: CUST-445 | F12: West | G12: Wholesale | H12: Home & Kitchen | I12: Mixer Grinder | J12: 12 | K12: 4200 | L12: =J12*K12 -> 50400 | M12: 8 | N12: =L12*(1-M12/100) -> 46368
A13: ORD-011 | B13: 2024-03-05 | C13: March | D13: Q1 | E13: CUST-678 | F13: North | G13: Online | H13: Sports | I13: Cricket Bat | J13: 7 | K13: 3500 | L13: =J13*K13 -> 24500 | M13: 10 | N13: =L13*(1-M13/100) -> 22050
A14: ORD-012 | B14: 2024-03-11 | C14: March | D14: Q1 | E14: CUST-901 | F14: South | G14: Retail Store | H14: Electronics | I14: Tablet | J14: 5 | K14: 32000 | L14: =J14*K14 -> 160000 | M14: 5 | N14: =L14*(1-M14/100) -> 152000
... A62: ORD-060 | B62: 2024-12-31 | C62: December | D62: Q4 | E62: CUST-179 | F62: Central | G62: Wholesale | H62: Sports | I62: New Year Kit | J62: 25 | K62: 3500 | L62: =J62*K62 -> 87500 | M62: 10 | N62: =L62*(1-M62/100) -> 78750
A63: GRAND TOTAL | J63: =SUM(J3:J62) -> 866 | L63: =SUM(L3:L62) -> 5361300 | N63: =SUM(N3:N62) -> 4871130

Sheet 🧹 Data Cleaning
A1: DATA CLEANING & PREPARATION · SHOPNEXUS FY 2024
A3: ▸ STEP 1 — DATA IMPORT & INSPECTION
A4: Check | B4: Finding | C4: Action Taken | D4: Status
A5: Total Records Imported | B5: 60 transaction records · FY 2024 | C5: Verified all rows loaded correctly | D5: ✅ Complete
A6: Columns | B6: 14 columns — Order ID to Net Revenue | C6: Headers standardized | D6: ✅ Complete
A7: Duplicate Orders | B7: 0 duplicates found | C7: No action needed | D7: ✅ Complete
A8: Missing Values | B8: Revenue & Net Revenue blank | C8: Applied formulas =Units×Price and =Rev×(1-Disc%) | D8: ✅ Complete
A9: Data Types | B9: Dates as text · prices as numbers | C9: Date column formatted · number format applied | D9: ✅ Complete
A10: Discount Column | B10: Stored as whole number (5 = 5%) | C10: Divided by 100 in Net Revenue formula | D10: ✅ Complete
A11: Negative Values | B11: No negative prices or units found | C11: No action needed | D11: ✅ Complete
A12: Blank Cells | B12: Revenue & Net Revenue columns blank | C12: Filled with live Excel formulas | D12: ✅ Complete
A14: ▸ STEP 2 — DERIVED COLUMNS ADDED
A15: New Column | B15: Formula Used | C15: Purpose
A16: Revenue (Rs.) | B16: Formula: Units multiplied by Unit Price | C16: Calculate gross revenue per order
A17: Net Revenue (Rs.) | B17: Formula: Revenue multiplied by (1 minus Discount Pct / 100) | C17: Revenue after discount deduction
A18: Quarter | B18: Assigned manually based on Month column | C18: Group orders into Q1 / Q2 / Q3 / Q4
A20: ▸ STEP 3 — DATA QUALITY SUMMARY
A21: Metric | B21: Value | C21: Assessment
A22: Total Orders | B22: 60 | C22: Complete FY 2024 dataset
A23: Date Range | B23: 01-Jan-2024 to 31-Dec-2024 | C23: Full year covered
A24: Unique Products | B24: 18 products across 6 categories | C24: Diverse product mix
A25: Regions | B25: 5 — North, South, East, West, Central | C25: Pan-India coverage
A26: Sales Channels | B26: 3 — Online, Retail Store, Wholesale | C26: Multi-channel data
A27: Discount Range | B27: 0% to 25% | C27: Reasonable range
A28: Completeness | B28: 100% — no missing critical data | C28: Ready for analysis
A29: Quality Rating | B29: EXCELLENT ✅ | C29: Approved for business reporting

Sheet 🏆 Product Analysis
A1: PRODUCT PERFORMANCE · BUSINESS Q1: WHICH PRODUCT SELLS MOST? · FY 2024
A3: ▸ CATEGORY-WISE BREAKDOWN
A4: Category | B4: Orders | C4: Units Sold | D4: Gross Revenue (₹) | E4: Net Revenue (₹) | F4: Avg Discount % | G4: Rev Share % | H4: Rank
A5: Electronics | B5: =COUNTIF('🛒 E-Commerce Dataset'!H:H,A5) -> 15 | C5: =SUMIF('🛒 E-Commerce Dataset'!H:H,A5,'🛒 E-Commerce Dataset'!J:J) -> 135 | D5: =SUMIF('🛒 E-Commerce Dataset'!H:H,A5,'🛒 E-Commerce Dataset'!L:L) -> 3428000 | E5: =SUMIF('🛒 E-Commerce Dataset'!H:H,A5,'🛒 E-Commerce Dataset'!N:N) -> 3175230 | F5: =_xlfn.IFERROR(_xlfn.AVERAGEIF('🛒 E-Commerce Dataset'!H:H,A5,'🛒 E-Commerce Dataset'!M:M),0) -> 6.5333333 | G5: =_xlfn.IFERROR(D5/SUM($D$5:$D$10),0) -> 0.63939716 | H5: =RANK(D5,$D$5:$D$10,0) -> 1
A6: Fashion | B6: =COUNTIF('🛒 E-Commerce Dataset'!H:H,A6) -> 10 | C6: =SUMIF('🛒 E-Commerce Dataset'!H:H,A6,'🛒 E-Commerce Dataset'!J:J) -> 170 | D6: =SUMIF('🛒 E-Commerce Dataset'!H:H,A6,'🛒 E-Commerce Dataset'!L:L) -> 485700 | E6: =SUMIF('🛒 E-Commerce Dataset'!H:H,A6,'🛒 E-Commerce Dataset'!N:N) -> 405050 | F6: =_xlfn.IFERROR(_xlfn.AVERAGEIF('🛒 E-Commerce Dataset'!H:H,A6,'🛒 E-Commerce Dataset'!M:M),0) -> 16 | G6: =_xlfn.IFERROR(D6/SUM($D$5:$D$10),0) -> 0.090593699 | H6: =RANK(D6,$D$5:$D$10,0) -> 3
A7: Home & Kitchen | B7: =COUNTIF('🛒 E-Commerce Dataset'!H:H,A7) -> 10 | C7: =SUMIF('🛒 E-Commerce Dataset'!H:H,A7,'🛒 E-Commerce Dataset'!J:J) -> 61 | D7: =SUMIF('🛒 E-Commerce Dataset'!H:H,A7,'🛒 E-Commerce Dataset'!L:L) -> 468800 | E7: =SUMIF('🛒 E-Commerce Dataset'!H:H,A7,'🛒 E-Commerce Dataset'!N:N) -> 429488 | F7: =_xlfn.IFERROR(_xlfn.AVERAGEIF('🛒 E-Commerce Dataset'!H:H,A7,'🛒 E-Commerce Dataset'!M:M),0) -> 8.4 | G7: =_xlfn.IFERROR(D7/SUM($D$5:$D$10),0) -> 0.087441479 | H7: =RANK(D7,$D$5:$D$10,0) -> 4
A8: Sports | B8: =COUNTIF('🛒 E-Commerce Dataset'!H:H,A8) -> 10 | C8: =SUMIF('🛒 E-Commerce Dataset'!H:H,A8,'🛒 E-Commerce Dataset'!J:J) -> 127 | D8: =SUMIF('🛒 E-Commerce Dataset'!H:H,A8,'🛒 E-Commerce Dataset'!L:L) -> 516000 | E8: =SUMIF('🛒 E-Commerce Dataset'!H:H,A8,'🛒 E-Commerce Dataset'!N:N) -> 455640 | F8: =_xlfn.IFERROR(_xlfn.AVERAGEIF('🛒 E-Commerce Dataset'!H:H,A8,'🛒 E-Commerce Dataset'!M:M),0) -> 11.4 | G8: =_xlfn.IFERROR(D8/SUM($D$5:$D$10),0) -> 0.096245314 | H8: =RANK(D8,$D$5:$D$10,0) -> 2
A9: Books | B9: =COUNTIF('🛒 E-Commerce Dataset'!H:H,A9) -> 7 | C9: =SUMIF('🛒 E-Commerce Dataset'!H:H,A9,'🛒 E-Commerce Dataset'!J:J) -> 215 | D9: =SUMIF('🛒 E-Commerce Dataset'!H:H,A9,'🛒 E-Commerce Dataset'!L:L) -> 104000 | E9: =SUMIF('🛒 E-Commerce Dataset'!H:H,A9,'🛒 E-Commerce Dataset'!N:N) -> 104000 | F9: =_xlfn.IFERROR(_xlfn.AVERAGEIF('🛒 E-Commerce Dataset'!H:H,A9,'🛒 E-Commerce Dataset'!M:M),0) -> 0 | G9: =_xlfn.IFERROR(D9/SUM($D$5:$D$10),0) -> 0.01939828 | H9: =RANK(D9,$D$5:$D$10,0) -> 6
A10: Beauty | B10: =COUNTIF('🛒 E-Commerce Dataset'!H:H,A10) -> 8 | C10: =SUMIF('🛒 E-Commerce Dataset'!H:H,A10,'🛒 E-Commerce Dataset'!J:J) -> 158 | D10: =SUMIF('🛒 E-Commerce Dataset'!H:H,A10,'🛒 E-Commerce Dataset'!L:L) -> 358800 | E10: =SUMIF('🛒 E-Commerce Dataset'!H:H,A10,'🛒 E-Commerce Dataset'!N:N) -> 301722 | F10: =_xlfn.IFERROR(_xlfn.AVERAGEIF('🛒 E-Commerce Dataset'!H:H,A10,'🛒 E-Commerce Dataset'!M:M),0) -> 16.375 | G10: =_xlfn.IFERROR(D10/SUM($D$5:$D$10),0) -> 0.066924067 | H10: =RANK(D10,$D$5:$D$10,0) -> 5
A11: TOTAL | B11: =SUM(B5:B10) -> 60 | C11: =SUM(C5:C10) -> 866 | D11: =SUM(D5:D10) -> 5361300 | E11: =SUM(E5:E10) -> 4871130 | F11: =AVERAGE(F5:F10) -> 9.7847222 | G11: =SUM(G5:G10) -> 1
A13: ▸ TOP 10 PRODUCTS BY REVENUE
A14: Product | B14: Category | C14: Orders | D14: Units | E14: Revenue (₹) | F14: Net Rev (₹) | G14: Avg Price (₹) | H14: Rank
A15: Laptop | B15: Electronics | C15: =COUNTIF('🛒 E-Commerce Dataset'!I:I,A15) -> 7 | D15: =SUMIF('🛒 E-Commerce Dataset'!I:I,A15,'🛒 E-Commerce Dataset'!J:J) -> 38 | E15: =SUMIF('🛒 E-Commerce Dataset'!I:I,A15,'🛒 E-Commerce Dataset'!L:L) -> 2204000 | F15: =SUMIF('🛒 E-Commerce Dataset'!I:I,A15,'🛒 E-Commerce Dataset'!N:N) -> 2021880 | G15: =_xlfn.IFERROR(E15/C15,0) -> 314857.14 | H15: =RANK(E15,$E$15:$E$24,0) -> 1
A16: Smart TV | B16: Electronics | C16: =COUNTIF('🛒 E-Commerce Dataset'!I:I,A16) -> 2 | D16: =SUMIF('🛒 E-Commerce Dataset'!I:I,A16,'🛒 E-Commerce Dataset'!J:J) -> 5 | E16: =SUMIF('🛒 E-Commerce Dataset'!I:I,A16,'🛒 E-Commerce Dataset'!L:L) -> 225000 | F16: =SUMIF('🛒 E-Commerce Dataset'!I:I,A16,'🛒 E-Commerce Dataset'!N:N) -> 204300 | G16: =_xlfn.IFERROR(E16/C16,0) -> 112500 | H16: =RANK(E16,$E$15:$E$24,0) -> 4
A17: Smart Watch | B17: Electronics | C17: =COUNTIF('🛒 E-Commerce Dataset'!I:I,A17) -> 2 | D17: =SUMIF('🛒 E-Commerce Dataset'!I:I,A17,'🛒 E-Commerce Dataset'!J:J) -> 25 | E17: =SUMIF('🛒 E-Commerce Dataset'!I:I,A17,'🛒 E-Commerce Dataset'!L:L) -> 450000 | F17: =SUMIF('🛒 E-Commerce Dataset'!I:I,A17,'🛒 E-Commerce Dataset'!N:N) -> 427500 | G17: =_xlfn.IFERROR(E17/C17,0) -> 225000 | H17: =RANK(E17,$E$15:$E$24,0) -> 2
A18: Smartphone | B18: Electronics | C18: =COUNTIF('🛒 E-Commerce Dataset'!I:I,A18) -> 2 | D18: =SUMIF('🛒 E-Commerce Dataset'!I:I,A18,'🛒 E-Commerce Dataset'!J:J) -> 12 | E18: =SUMIF('🛒 E-Commerce Dataset'!I:I,A18,'🛒 E-Commerce Dataset'!L:L) -> 264000 | F18: =SUMIF('🛒 E-Commerce Dataset'!I:I,A18,'🛒 E-Commerce Dataset'!N:N) -> 250800 | G18: =_xlfn.IFERROR(E18/C18,0) -> 132000 | H18: =RANK(E18,$E$15:$E$24,0) -> 3
A19: Tablet | B19: Electronics | C19: =COUNTIF('🛒 E-Commerce Dataset'!I:I,A19) -> 1 | D19: =SUMIF('🛒 E-Commerce Dataset'!I:I,A19,'🛒 E-Commerce Dataset'!J:J) -> 5 | E19: =SUMIF('🛒 E-Commerce Dataset'!I:I,A19,'🛒 E-Commerce Dataset'!L:L) -> 160000 | F19: =SUMIF('🛒 E-Commerce Dataset'!I:I,A19,'🛒 E-Commerce Dataset'!N:N) -> 152000 | G19: =_xlfn.IFERROR(E19/C19,0) -> 160000 | H19: =RANK(E19,$E$15:$E$24,0) -> 5
A20: Designer Saree | B20: Fashion | C20: =COUNTIF('🛒 E-Commerce Dataset'!I:I,A20) -> 1 | D20: =SUMIF('🛒 E-Commerce Dataset'!I:I,A20,'🛒 E-Commerce Dataset'!J:J) -> 8 | E20: =SUMIF('🛒 E-Commerce Dataset'!I:I,A20,'🛒 E-Commerce Dataset'!L:L) -> 36000 | F20: =SUMIF('🛒 E-Commerce Dataset'!I:I,A20,'🛒 E-Commerce Dataset'!N:N) -> 30600 | G20: =_xlfn.IFERROR(E20/C20,0) -> 36000 | H20: =RANK(E20,$E$15:$E$24,0) -> 9
A21: Running Shoes | B21: Fashion | C21: =COUNTIF('🛒 E-Commerce Dataset'!I:I,A21) -> 1 | D21: =SUMIF('🛒 E-Commerce Dataset'!I:I,A21,'🛒 E-Commerce Dataset'!J:J) -> 5 | E21: =SUMIF('🛒 E-Commerce Dataset'!I:I,A21,'🛒 E-Commerce Dataset'!L:L) -> 22500 | F21: =SUMIF('🛒 E-Commerce Dataset'!I:I,A21,'🛒 E-Commerce Dataset'!N:N) -> 20250 | G21: =_xlfn.IFERROR(E21/C21,0) -> 22500 | H21: =RANK(E21,$E$15:$E$24,0) -> 10
A22: Water Purifier | B22: Home & Kitchen | C22: =COUNTIF('🛒 E-Commerce Dataset'!I:I,A22) -> 1 | D22: =SUMIF('🛒 E-Commerce Dataset'!I:I,A22,'🛒 E-Commerce Dataset'!J:J) -> 4 | E22: =SUMIF('🛒 E-Commerce Dataset'!I:I,A22,'🛒 E-Commerce Dataset'!L:L) -> 48000 | F22: =SUMIF('🛒 E-Commerce Dataset'!I:I,A22,'🛒 E-Commerce Dataset'!N:N) -> 44160 | G22: =_xlfn.IFERROR(E22/C22,0) -> 48000 | H22: =RANK(E22,$E$15:$E$24,0) -> 7
A23: Treadmill | B23: Sports | C23: =COUNTIF('🛒 E-Commerce Dataset'!I:I,A23) -> 1 | D23: =SUMIF('🛒 E-Commerce Dataset'!I:I,A23,'🛒 E-Commerce Dataset'!J:J) -> 1 | E23: =SUMIF('🛒 E-Commerce Dataset'!I:I,A23,'🛒 E-Commerce Dataset'!L:L) -> 45000 | F23: =SUMIF('🛒 E-Commerce Dataset'!I:I,A23,'🛒 E-Commerce Dataset'!N:N) -> 40500 | G23: =_xlfn.IFERROR(E23/C23,0) -> 45000 | H23: =RANK(E23,$E$15:$E$24,0) -> 8
A24: Multi Gym | B24: Sports | C24: =COUNTIF('🛒 E-Commerce Dataset'!I:I,A24) -> 1 | D24: =SUMIF('🛒 E-Commerce Dataset'!I:I,A24,'🛒 E-Commerce Dataset'!J:J) -> 2 | E24: =SUMIF('🛒 E-Commerce Dataset'!I:I,A24,'🛒 E-Commerce Dataset'!L:L) -> 110000 | F24: =SUMIF('🛒 E-Commerce Dataset'!I:I,A24,'🛒 E-Commerce Dataset'!N:N) -> 93500 | G24: =_xlfn.IFERROR(E24/C24,0) -> 110000 | H24: =RANK(E24,$E$15:$E$24,0) -> 6

Sheet 🌍 Regional Analysis
A1: REGIONAL PERFORMANCE · BUSINESS Q2: WHICH REGION PERFORMS BEST? · FY 2024
A3: ▸ REGION-WISE REVENUE BREAKDOWN
A4: Region | B4: Orders | C4: Units Sold | D4: Gross Revenue (₹) | E4: Net Revenue (₹) | F4: Avg Order Value (₹) | G4: Rev Share % | H4: Rank
A5: South | B5: =COUNTIF('🛒 E-Commerce Dataset'!F:F,A5) -> 16 | C5: =SUMIF('🛒 E-Commerce Dataset'!F:F,A5,'🛒 E-Commerce Dataset'!J:J) -> 258 | D5: =SUMIF('🛒 E-Commerce Dataset'!F:F,A5,'🛒 E-Commerce Dataset'!L:L) -> 2449000 | E5: =SUMIF('🛒 E-Commerce Dataset'!F:F,A5,'🛒 E-Commerce Dataset'!N:N) -> 2238910 | F5: =_xlfn.IFERROR(D5/B5,0) -> 153062.5 | G5: =_xlfn.IFERROR(D5/SUM($D$5:$D$9),0) -> 0.4567922 | H5: =RANK(D5,$D$5:$D$9,0) -> 1
A6: North | B6: =COUNTIF('🛒 E-Commerce Dataset'!F:F,A6) -> 12 | C6: =SUMIF('🛒 E-Commerce Dataset'!F:F,A6,'🛒 E-Commerce Dataset'!J:J) -> 76 | D6: =SUMIF('🛒 E-Commerce Dataset'!F:F,A6,'🛒 E-Commerce Dataset'!L:L) -> 1547000 | E6: =SUMIF('🛒 E-Commerce Dataset'!F:F,A6,'🛒 E-Commerce Dataset'!N:N) -> 1413350 | F6: =_xlfn.IFERROR(D6/B6,0) -> 128916.67 | G6: =_xlfn.IFERROR(D6/SUM($D$5:$D$9),0) -> 0.28854942 | H6: =RANK(D6,$D$5:$D$9,0) -> 2
A7: West | B7: =COUNTIF('🛒 E-Commerce Dataset'!F:F,A7) -> 12 | C7: =SUMIF('🛒 E-Commerce Dataset'!F:F,A7,'🛒 E-Commerce Dataset'!J:J) -> 157 | D7: =SUMIF('🛒 E-Commerce Dataset'!F:F,A7,'🛒 E-Commerce Dataset'!L:L) -> 704300 | E7: =SUMIF('🛒 E-Commerce Dataset'!F:F,A7,'🛒 E-Commerce Dataset'!N:N) -> 624248 | F7: =_xlfn.IFERROR(D7/B7,0) -> 58691.667 | G7: =_xlfn.IFERROR(D7/SUM($D$5:$D$9),0) -> 0.13136739 | H7: =RANK(D7,$D$5:$D$9,0) -> 3
A8: East | B8: =COUNTIF('🛒 E-Commerce Dataset'!F:F,A8) -> 12 | C8: =SUMIF('🛒 E-Commerce Dataset'!F:F,A8,'🛒 E-Commerce Dataset'!J:J) -> 135 | D8: =SUMIF('🛒 E-Commerce Dataset'!F:F,A8,'🛒 E-Commerce Dataset'!L:L) -> 469500 | E8: =SUMIF('🛒 E-Commerce Dataset'!F:F,A8,'🛒 E-Commerce Dataset'!N:N) -> 411872 | F8: =_xlfn.IFERROR(D8/B8,0) -> 39125 | G8: =_xlfn.IFERROR(D8/SUM($D$5:$D$9),0) -> 0.087572044 | H8: =RANK(D8,$D$5:$D$9,0) -> 4
A9: Central | B9: =COUNTIF('🛒 E-Commerce Dataset'!F:F,A9) -> 8 | C9: =SUMIF('🛒 E-Commerce Dataset'!F:F,A9,'🛒 E-Commerce Dataset'!J:J) -> 240 | D9: =SUMIF('🛒 E-Commerce Dataset'!F:F,A9,'🛒 E-Commerce Dataset'!L:L) -> 191500 | E9: =SUMIF('🛒 E-Commerce Dataset'!F:F,A9,'🛒 E-Commerce Dataset'!N:N) -> 182750 | F9: =_xlfn.IFERROR(D9/B9,0) -> 23937.5 | G9: =_xlfn.IFERROR(D9/SUM($D$5:$D$9),0) -> 0.035718949 | H9: =RANK(D9,$D$5:$D$9,0) -> 5
A10: TOTAL | B10: =SUM(B5:B9) -> 60 | C10: =SUM(C5:C9) -> 866 | D10: =SUM(D5:D9) -> 5361300 | E10: =SUM(E5:E9) -> 4871130 | F10: =AVERAGE(F5:F9) -> 80746.667 | G10: =SUM(G5:G9) -> 1
A12: ▸ REGION × CHANNEL CROSS ANALYSIS
A13: Region | B13: Channel | C13: Orders | D13: Revenue (₹) | E13: Net Revenue (₹) | F13: Avg Discount %
A14: South | B14: Online | C14: =_xlfn.COUNTIFS('🛒 E-Commerce Dataset'!F:F,A14,'🛒 E-Commerce Dataset'!G:G,B14) -> 11 | D14: =_xlfn.SUMIFS('🛒 E-Commerce Dataset'!L:L,'🛒 E-Commerce Dataset'!F:F,A14,'🛒 E-Commerce Dataset'!G:G,B14) -> 2022000 | E14: =_xlfn.SUMIFS('🛒 E-Commerce Dataset'!N:N,'🛒 E-Commerce Dataset'!F:F,A14,'🛒 E-Commerce Dataset'!G:G,B14) -> 1846320 | F14: =_xlfn.IFERROR(_xlfn.AVERAGEIFS('🛒 E-Commerce Dataset'!M:M,'🛒 E-Commerce Dataset'!F:F,A14,'🛒 E-Commerce Dataset'!G:G,B14),0) -> 10
A15: South | B15: Retail Store | C15: =_xlfn.COUNTIFS('🛒 E-Commerce Dataset'!F:F,A15,'🛒 E-Commerce Dataset'!G:G,B15) -> 1 | D15: =_xlfn.SUMIFS('🛒 E-Commerce Dataset'!L:L,'🛒 E-Commerce Dataset'!F:F,A15,'🛒 E-Commerce Dataset'!G:G,B15) -> 160000 | E15: =_xlfn.SUMIFS('🛒 E-Commerce Dataset'!N:N,'🛒 E-Commerce Dataset'!F:F,A15,'🛒 E-Commerce Dataset'!G:G,B15) -> 152000 | F15: =_xlfn.IFERROR(_xlfn.AVERAGEIFS('🛒 E-Commerce Dataset'!M:M,'🛒 E-Commerce Dataset'!F:F,A15,'🛒 E-Commerce Dataset'!G:G,B15),0) -> 5
A16: South | B16: Wholesale | C16: =_xlfn.COUNTIFS('🛒 E-Commerce Dataset'!F:F,A16,'🛒 E-Commerce Dataset'!G:G,B16) -> 4 | D16: =_xlfn.SUMIFS('🛒 E-Commerce Dataset'!L:L,'🛒 E-Commerce Dataset'!F:F,A16,'🛒 E-Commerce Dataset'!G:G,B16) -> 267000 | E16: =_xlfn.SUMIFS('🛒 E-Commerce Dataset'!N:N,'🛒 E-Commerce Dataset'!F:F,A16,'🛒 E-Commerce Dataset'!G:G,B16) -> 240590 | F16: =_xlfn.IFERROR(_xlfn.AVERAGEIFS('🛒 E-Commerce Dataset'!M:M,'🛒 E-Commerce Dataset'!F:F,A16,'🛒 E-Commerce Dataset'!G:G,B16),0) -> 13
A17: North | B17: Online | C17: =_xlfn.COUNTIFS('🛒 E-Commerce Dataset'!F:F,A17,'🛒 E-Commerce Dataset'!G:G,B17) -> 11 | D17: =_xlfn.SUMIFS('🛒 E-Commerce Dataset'!L:L,'🛒 E-Commerce Dataset'!F:F,A17,'🛒 E-Commerce Dataset'!G:G,B17) -> 1524500 | E17: =_xlfn.SUMIFS('🛒 E-Commerce Dataset'!N:N,'🛒 E-Commerce Dataset'!F:F,A17,'🛒 E-Commerce Dataset'!G:G,B17) -> 1393100 | F17: =_xlfn.IFERROR(_xlfn.AVERAGEIFS('🛒 E-Commerce Dataset'!M:M,'🛒 E-Commerce Dataset'!F:F,A17,'🛒 E-Commerce Dataset'!G:G,B17),0) -> 10.454545
A18: North | B18: Retail Store | C18: =_xlfn.COUNTIFS('🛒 E-Commerce Dataset'!F:F,A18,'🛒 E-Commerce Dataset'!G:G,B18) -> 1 | D18: =_xlfn.SUMIFS('🛒 E-Commerce Dataset'!L:L,'🛒 E-Commerce Dataset'!F:F,A18,'🛒 E-Commerce Dataset'!G:G,B18) -> 22500 | E18: =_xlfn.SUMIFS('🛒 E-Commerce Dataset'!N:N,'🛒 E-Commerce Dataset'!F:F,A18,'🛒 E-Commerce Dataset'!G:G,B18) -> 20250 | F18: =_xlfn.IFERROR(_xlfn.AVERAGEIFS('🛒 E-Commerce Dataset'!M:M,'🛒 E-Commerce Dataset'!F:F,A18,'🛒 E-Commerce Dataset'!G:G,B18),0) -> 10
A19: North | B19: Wholesale | C19: =_xlfn.COUNTIFS('🛒 E-Commerce Dataset'!F:F,A19,'🛒 E-Commerce Dataset'!G:G,B19) -> 0 | D19: =_xlfn.SUMIFS('🛒 E-Commerce Dataset'!L:L,'🛒 E-Commerce Dataset'!F:F,A19,'🛒 E-Commerce Dataset'!G:G,B19) -> 0 | E19: =_xlfn.SUMIFS('🛒 E-Commerce Dataset'!N:N,'🛒 E-Commerce Dataset'!F:F,A19,'🛒 E-Commerce Dataset'!G:G,B19) -> 0 | F19: =_xlfn.IFERROR(_xlfn.AVERAGEIFS('🛒 E-Commerce Dataset'!M:M,'🛒 E-Commerce Dataset'!F:F,A19,'🛒 E-Commerce Dataset'!G:G,B19),0) -> 0
A20: East | B20: Online | C20: =_xlfn.COUNTIFS('🛒 E-Commerce Dataset'!F:F,A20,'🛒 E-Commerce Dataset'!G:G,B20) -> 6 | D20: =_xlfn.SUMIFS('🛒 E-Commerce Dataset'!L:L,'🛒 E-Commerce Dataset'!F:F,A20,'🛒 E-Commerce Dataset'!G:G,B20) -> 206100 | E20: =_xlfn.SUMIFS('🛒 E-Commerce Dataset'!N:N,'🛒 E-Commerce Dataset'!F:F,A20,'🛒 E-Commerce Dataset'!G:G,B20) -> 184120 | F20: =_xlfn.IFERROR(_xlfn.AVERAGEIFS('🛒 E-Commerce Dataset'!M:M,'🛒 E-Commerce Dataset'!F:F,A20,'🛒 E-Commerce Dataset'!G:G,B20),0) -> 11.833333
A21: East | B21: Retail Store | C21: =_xlfn.COUNTIFS('🛒 E-Commerce Dataset'!F:F,A21,'🛒 E-Commerce Dataset'!G:G,B21) -> 6 | D21: =_xlfn.SUMIFS('🛒 E-Commerce Dataset'!L:L,'🛒 E-Commerce Dataset'!F:F,A21,'🛒 E-Commerce Dataset'!G:G,B21) -> 263400 | E21: =_xlfn.SUMIFS('🛒 E-Commerce Dataset'!N:N,'🛒 E-Commerce Dataset'!F:F,A21,'🛒 E-Commerce Dataset'!G:G,B21) -> 227752 | F21: =_xlfn.IFERROR(_xlfn.AVERAGEIFS('🛒 E-Commerce Dataset'!M:M,'🛒 E-Commerce Dataset'!F:F,A21,'🛒 E-Commerce Dataset'!G:G,B21),0) -> 13.166667
A22: West | B22: Online | C22: =_xlfn.COUNTIFS('🛒 E-Commerce Dataset'!F:F,A22,'🛒 E-Commerce Dataset'!G:G,B22) -> 8 | D22: =_xlfn.SUMIFS('🛒 E-Commerce Dataset'!L:L,'🛒 E-Commerce Dataset'!F:F,A22,'🛒 E-Commerce Dataset'!G:G,B22) -> 453900 | E22: =_xlfn.SUMIFS('🛒 E-Commerce Dataset'!N:N,'🛒 E-Commerce Dataset'!F:F,A22,'🛒 E-Commerce Dataset'!G:G,B22) -> 404940 | F22: =_xlfn.IFERROR(_xlfn.AVERAGEIFS('🛒 E-Commerce Dataset'!M:M,'🛒 E-Commerce Dataset'!F:F,A22,'🛒 E-Commerce Dataset'!G:G,B22),0) -> 11.125
A23: West | B23: Wholesale | C23: =_xlfn.COUNTIFS('🛒 E-Commerce Dataset'!F:F,A23,'🛒 E-Commerce Dataset'!G:G,B23) -> 4 | D23: =_xlfn.SUMIFS('🛒 E-Commerce Dataset'!L:L,'🛒 E-Commerce Dataset'!F:F,A23,'🛒 E-Commerce Dataset'!G:G,B23) -> 250400 | E23: =_xlfn.SUMIFS('🛒 E-Commerce Dataset'!N:N,'🛒 E-Commerce Dataset'!F:F,A23,'🛒 E-Commerce Dataset'!G:G,B23) -> 219308 | F23: =_xlfn.IFERROR(_xlfn.AVERAGEIFS('🛒 E-Commerce Dataset'!M:M,'🛒 E-Commerce Dataset'!F:F,A23,'🛒 E-Commerce Dataset'!G:G,B23),0) -> 11.5
A24: Central | B24: Retail Store | C24: =_xlfn.COUNTIFS('🛒 E-Commerce Dataset'!F:F,A24,'🛒 E-Commerce Dataset'!G:G,B24) -> 4 | D24: =_xlfn.SUMIFS('🛒 E-Commerce Dataset'!L:L,'🛒 E-Commerce Dataset'!F:F,A24,'🛒 E-Commerce Dataset'!G:G,B24) -> 62500 | E24: =_xlfn.SUMIFS('🛒 E-Commerce Dataset'!N:N,'🛒 E-Commerce Dataset'!F:F,A24,'🛒 E-Commerce Dataset'!G:G,B24) -> 62500 | F24: =_xlfn.IFERROR(_xlfn.AVERAGEIFS('🛒 E-Commerce Dataset'!M:M,'🛒 E-Commerce Dataset'!F:F,A24,'🛒 E-Commerce Dataset'!G:G,B24),0) -> 0
A25: Central | B25: Wholesale | C25: =_xlfn.COUNTIFS('🛒 E-Commerce Dataset'!F:F,A25,'🛒 E-Commerce Dataset'!G:G,B25) -> 4 | D25: =_xlfn.SUMIFS('🛒 E-Commerce Dataset'!L:L,'🛒 E-Commerce Dataset'!F:F,A25,'🛒 E-Commerce Dataset'!G:G,B25) -> 129000 | E25: =_xlfn.SUMIFS('🛒 E-Commerce Dataset'!N:N,'🛒 E-Commerce Dataset'!F:F,A25,'🛒 E-Commerce Dataset'!G:G,B25) -> 120250 | F25: =_xlfn.IFERROR(_xlfn.AVERAGEIFS('🛒 E-Commerce Dataset'!M:M,'🛒 E-Commerce Dataset'!F:F,A25,'🛒 E-Commerce Dataset'!G:G,B25),0) -> 2.5

Sheet 📝 SQL Queries
A1: SQL DATA ANALYSIS QUERIES · WEEK 4 BUSINESS CASE STUDY · SHOPNEXUS
A3: ● Q1 — CREATE TABLE SCHEMA
A4: CREATE DATABASE shopnexus;
A5: USE shopnexus;
A7: CREATE TABLE ecommerce_sales (
A8: order_id VARCHAR(15) PRIMARY KEY,
A9: order_date DATE,
A10: month VARCHAR(15),
A11: quarter VARCHAR(5),
A12: customer_id VARCHAR(15),
A13: region VARCHAR(20),
A14: channel VARCHAR(20),
... A107: ORDER BY total_spend DESC;

Sheet 📅 Monthly Trends
A1: MONTHLY SALES TRENDS · FY 2024
A2: Month | B2: Quarter | C2: Orders | D2: Units | E2: Gross Rev (₹) | F2: Net Rev (₹) | G2: MoM Growth % | H2: Cumulative (₹) | I2: % of Year
A3: January | B3: Q1 | C3: =COUNTIF('🛒 E-Commerce Dataset'!C:C,A3) -> 5 | D3: =SUMIF('🛒 E-Commerce Dataset'!C:C,A3,'🛒 E-Commerce Dataset'!J:J) -> 34 | E3: =SUMIF('🛒 E-Commerce Dataset'!C:C,A3,'🛒 E-Commerce Dataset'!L:L) -> 276000 | F3: =SUMIF('🛒 E-Commerce Dataset'!C:C,A3,'🛒 E-Commerce Dataset'!N:N) -> 257910 | G3: — | H3: =SUM($E$3:E3) -> 276000 | I3: =_xlfn.IFERROR(E3/SUM($E$3:$E$14),0) -> 0.051480051
A4: February | B4: Q1 | C4: =COUNTIF('🛒 E-Commerce Dataset'!C:C,A4) -> 5 | D4: =SUMIF('🛒 E-Commerce Dataset'!C:C,A4,'🛒 E-Commerce Dataset'!J:J) -> 51 | E4: =SUMIF('🛒 E-Commerce Dataset'!C:C,A4,'🛒 E-Commerce Dataset'!L:L) -> 284950 | F4: =SUMIF('🛒 E-Commerce Dataset'!C:C,A4,'🛒 E-Commerce Dataset'!N:N) -> 265198 | G4: =_xlfn.IFERROR((E4-E3)/E3,0) -> 0.032427536 | H4: =SUM($E$3:E4) -> 560950 | I4: =_xlfn.IFERROR(E4/SUM($E$3:$E$14),0) -> 0.053149423
A5: March | B5: Q1 | C5: =COUNTIF('🛒 E-Commerce Dataset'!C:C,A5) -> 5 | D5: =SUMIF('🛒 E-Commerce Dataset'!C:C,A5,'🛒 E-Commerce Dataset'!J:J) -> 72 | E5: =SUMIF('🛒 E-Commerce Dataset'!C:C,A5,'🛒 E-Commerce Dataset'!L:L) -> 256800 | F5: =SUMIF('🛒 E-Commerce Dataset'!C:C,A5,'🛒 E-Commerce Dataset'!N:N) -> 239150 | G5: =_xlfn.IFERROR((E5-E4)/E4,0) -> -0.098789261 | H5: =SUM($E$3:E5) -> 817750 | I5: =_xlfn.IFERROR(E5/SUM($E$3:$E$14),0) -> 0.047898831
A6: April | B6: Q2 | C6: =COUNTIF('🛒 E-Commerce Dataset'!C:C,A6) -> 5 | D6: =SUMIF('🛒 E-Commerce Dataset'!C:C,A6,'🛒 E-Commerce Dataset'!J:J) -> 75 | E6: =SUMIF('🛒 E-Commerce Dataset'!C:C,A6,'🛒 E-Commerce Dataset'!L:L) -> 408000 | F6: =SUMIF('🛒 E-Commerce Dataset'!C:C,A6,'🛒 E-Commerce Dataset'!N:N) -> 380810 | G6: =_xlfn.IFERROR((E6-E5)/E5,0) -> 0.58878505 | H6: =SUM($E$3:E6) -> 1225750 | I6: =_xlfn.IFERROR(E6/SUM($E$3:$E$14),0) -> 0.076100946
A7: May | B7: Q2 | C7: =COUNTIF('🛒 E-Commerce Dataset'!C:C,A7) -> 5 | D7: =SUMIF('🛒 E-Commerce Dataset'!C:C,A7,'🛒 E-Commerce Dataset'!J:J) -> 80 | E7: =SUMIF('🛒 E-Commerce Dataset'!C:C,A7,'🛒 E-Commerce Dataset'!L:L) -> 209150 | F7: =SUMIF('🛒 E-Commerce Dataset'!C:C,A7,'🛒 E-Commerce Dataset'!N:N) -> 186310 | G7: =_xlfn.IFERROR((E7-E6)/E6,0) -> -0.48737745 | H7: =SUM($E$3:E7) -> 1434900 | I7: =_xlfn.IFERROR(E7/SUM($E$3:$E$14),0) -> 0.039011061
A8: June | B8: Q2 | C8: =COUNTIF('🛒 E-Commerce Dataset'!C:C,A8) -> 5 | D8: =SUMIF('🛒 E-Commerce Dataset'!C:C,A8,'🛒 E-Commerce Dataset'!J:J) -> 85 | E8: =SUMIF('🛒 E-Commerce Dataset'!C:C,A8,'🛒 E-Commerce Dataset'!L:L) -> 394400 | F8: =SUMIF('🛒 E-Commerce Dataset'!C:C,A8,'🛒 E-Commerce Dataset'!N:N) -> 361432 | G8: =_xlfn.IFERROR((E8-E7)/E7,0) -> 0.88572795 | H8: =SUM($E$3:E8) -> 1829300 | I8: =_xlfn.IFERROR(E8/SUM($E$3:$E$14),0) -> 0.073564247
A9: July | B9: Q3 | C9: =COUNTIF('🛒 E-Commerce Dataset'!C:C,A9) -> 5 | D9: =SUMIF('🛒 E-Commerce Dataset'!C:C,A9,'🛒 E-Commerce Dataset'!J:J) -> 51 | E9: =SUMIF('🛒 E-Commerce Dataset'!C:C,A9,'🛒 E-Commerce Dataset'!L:L) -> 313500 | F9: =SUMIF('🛒 E-Commerce Dataset'!C:C,A9,'🛒 E-Commerce Dataset'!N:N) -> 287100 | G9: =_xlfn.IFERROR((E9-E8)/E8,0) -> -0.2051217 | H9: =SUM($E$3:E9) -> 2142800 | I9: =_xlfn.IFERROR(E9/SUM($E$3:$E$14),0) -> 0.058474624
A10: August | B10: Q3 | C10: =COUNTIF('🛒 E-Commerce Dataset'!C:C,A10) -> 5 | D10: =SUMIF('🛒 E-Commerce Dataset'!C:C,A10,'🛒 E-Commerce Dataset'!J:J) -> 50 | E10: =SUMIF('🛒 E-Commerce Dataset'!C:C,A10,'🛒 E-Commerce Dataset'!L:L) -> 446000 | F10: =SUMIF('🛒 E-Commerce Dataset'!C:C,A10,'🛒 E-Commerce Dataset'!N:N) -> 417280 | G10: =_xlfn.IFERROR((E10-E9)/E9,0) -> 0.42264753 | H10: =SUM($E$3:E10) -> 2588800 | I10: =_xlfn.IFERROR(E10/SUM($E$3:$E$14),0) -> 0.083188779
A11: September | B11: Q3 | C11: =COUNTIF('🛒 E-Commerce Dataset'!C:C,A11) -> 5 | D11: =SUMIF('🛒 E-Commerce Dataset'!C:C,A11,'🛒 E-Commerce Dataset'!J:J) -> 93 | E11: =SUMIF('🛒 E-Commerce Dataset'!C:C,A11,'🛒 E-Commerce Dataset'!L:L) -> 452000 | F11: =SUMIF('🛒 E-Commerce Dataset'!C:C,A11,'🛒 E-Commerce Dataset'!N:N) -> 414450 | G11: =_xlfn.IFERROR((E11-E10)/E10,0) -> 0.013452915 | H11: =SUM($E$3:E11) -> 3040800 | I11: =_xlfn.IFERROR(E11/SUM($E$3:$E$14),0) -> 0.08430791
A12: October | B12: Q4 | C12: =COUNTIF('🛒 E-Commerce Dataset'!C:C,A12) -> 5 | D12: =SUMIF('🛒 E-Commerce Dataset'!C:C,A12,'🛒 E-Commerce Dataset'!J:J) -> 100 | E12: =SUMIF('🛒 E-Commerce Dataset'!C:C,A12,'🛒 E-Commerce Dataset'!L:L) -> 628000 | F12: =SUMIF('🛒 E-Commerce Dataset'!C:C,A12,'🛒 E-Commerce Dataset'!N:N) -> 567400 | G12: =_xlfn.IFERROR((E12-E11)/E11,0) -> 0.38938053 | H12: =SUM($E$3:E12) -> 3668800 | I12: =_xlfn.IFERROR(E12/SUM($E$3:$E$14),0) -> 0.11713577
A13: November | B13: Q4 | C13: =COUNTIF('🛒 E-Commerce Dataset'!C:C,A13) -> 4 | D13: =SUMIF('🛒 E-Commerce Dataset'!C:C,A13,'🛒 E-Commerce Dataset'!J:J) -> 63 | E13: =SUMIF('🛒 E-Commerce Dataset'!C:C,A13,'🛒 E-Commerce Dataset'!L:L) -> 679000 | F13: =SUMIF('🛒 E-Commerce Dataset'!C:C,A13,'🛒 E-Commerce Dataset'!N:N) -> 605340 | G13: =_xlfn.IFERROR((E13-E12)/E12,0) -> 0.081210191 | H13: =SUM($E$3:E13) -> 4347800 | I13: =_xlfn.IFERROR(E13/SUM($E$3:$E$14),0) -> 0.12664839
A14: December | B14: Q4 | C14: =COUNTIF('🛒 E-Commerce Dataset'!C:C,A14) -> 6 | D14: =SUMIF('🛒 E-Commerce Dataset'!C:C,A14,'🛒 E-Commerce Dataset'!J:J) -> 112 | E14: =SUMIF('🛒 E-Commerce Dataset'!C:C,A14,'🛒 E-Commerce Dataset'!L:L) -> 1013500 | F14: =SUMIF('🛒 E-Commerce Dataset'!C:C,A14,'🛒 E-Commerce Dataset'!N:N) -> 888750 | G14: =_xlfn.IFERROR((E14-E13)/E13,0) -> 0.49263623 | H14: =SUM($E$3:E14) -> 5361300 | I14: =_xlfn.IFERROR(E14/SUM($E$3:$E$14),0) -> 0.18903997
A15: FULL YEAR | C15: =SUM(C3:C14) -> 60 | D15: =SUM(D3:D14) -> 866 | E15: =SUM(E3:E14) -> 5361300 | F15: =SUM(F3:F14) -> 4871130 | H15: =E15 -> 5361300 | I15: =SUM(I3:I14) -> 1

Sheet 📊 Quarterly Report
A1: QUARTERLY PERFORMANCE REPORT · FY 2024
A2: Quarter | B2: Period | C2: Orders | D2: Units | E2: Gross Rev (₹) | F2: Net Rev (₹) | G2: QoQ Growth % | H2: Avg Discount %
A3: Q1 | B3: Jan–Mar | C3: =COUNTIF('🛒 E-Commerce Dataset'!D:D,A3) -> 15 | D3: =SUMIF('🛒 E-Commerce Dataset'!D:D,A3,'🛒 E-Commerce Dataset'!J:J) -> 157 | E3: =SUMIF('🛒 E-Commerce Dataset'!D:D,A3,'🛒 E-Commerce Dataset'!L:L) -> 817750 | F3: =SUMIF('🛒 E-Commerce Dataset'!D:D,A3,'🛒 E-Commerce Dataset'!N:N) -> 762258 | G3: — | H3: =_xlfn.IFERROR(_xlfn.AVERAGEIF('🛒 E-Commerce Dataset'!D:D,A3,'🛒 E-Commerce Dataset'!M:M),0) -> 8.5333333
A4: Q2 | B4: Apr–Jun | C4: =COUNTIF('🛒 E-Commerce Dataset'!D:D,A4) -> 15 | D4: =SUMIF('🛒 E-Commerce Dataset'!D:D,A4,'🛒 E-Commerce Dataset'!J:J) -> 240 | E4: =SUMIF('🛒 E-Commerce Dataset'!D:D,A4,'🛒 E-Commerce Dataset'!L:L) -> 1011550 | F4: =SUMIF('🛒 E-Commerce Dataset'!D:D,A4,'🛒 E-Commerce Dataset'!N:N) -> 928552 | G4: =_xlfn.IFERROR((E4-E3)/E3,0) -> 0.23699175 | H4: =_xlfn.IFERROR(_xlfn.AVERAGEIF('🛒 E-Commerce Dataset'!D:D,A4,'🛒 E-Commerce Dataset'!M:M),0) -> 9.8666667
A5: Q3 | B5: Jul–Sep | C5: =COUNTIF('🛒 E-Commerce Dataset'!D:D,A5) -> 15 | D5: =SUMIF('🛒 E-Commerce Dataset'!D:D,A5,'🛒 E-Commerce Dataset'!J:J) -> 194 | E5: =SUMIF('🛒 E-Commerce Dataset'!D:D,A5,'🛒 E-Commerce Dataset'!L:L) -> 1211500 | F5: =SUMIF('🛒 E-Commerce Dataset'!D:D,A5,'🛒 E-Commerce Dataset'!N:N) -> 1118830 | G5: =_xlfn.IFERROR((E5-E4)/E4,0) -> 0.19766695 | H5: =_xlfn.IFERROR(_xlfn.AVERAGEIF('🛒 E-Commerce Dataset'!D:D,A5,'🛒 E-Commerce Dataset'!M:M),0) -> 9.5333333
A6: Q4 | B6: Oct–Dec | C6: =COUNTIF('🛒 E-Commerce Dataset'!D:D,A6) -> 15 | D6: =SUMIF('🛒 E-Commerce Dataset'!D:D,A6,'🛒 E-Commerce Dataset'!J:J) -> 275 | E6: =SUMIF('🛒 E-Commerce Dataset'!D:D,A6,'🛒 E-Commerce Dataset'!L:L) -> 2320500 | F6: =SUMIF('🛒 E-Commerce Dataset'!D:D,A6,'🛒 E-Commerce Dataset'!N:N) -> 2061490 | G6: =_xlfn.IFERROR((E6-E5)/E5,0) -> 0.91539414 | H6: =_xlfn.IFERROR(_xlfn.AVERAGEIF('🛒 E-Commerce Dataset'!D:D,A6,'🛒 E-Commerce Dataset'!M:M),0) -> 11.2
A7: FULL YEAR | C7: =SUM(C3:C6) -> 60 | D7: =SUM(D3:D6) -> 866 | E7: =SUM(E3:E6) -> 5361300 | F7: =SUM(F3:F6) -> 4871130 | H7: =AVERAGE(H3:H6) -> 9.7833333

Sheet 💡 Insights Report
A1: BUSINESS INSIGHTS REPORT · SHOPNEXUS · FY 2024
A3: 📋 EXECUTIVE SUMMARY
A4: Company: | D4: ShopNexus E-Commerce Platform — Pan-India Operations
A5: Analysis Period: | D5: FY 2024 (January 2024 – December 2024)
A6: Dataset: | D6: 60 orders · 6 categories · 18 products · 5 regions · 3 channels
A7: Business Questions: | D7: Q1: Which product sells most? | Q2: Which region performs best?
A8: Prepared by: | D8: Mohammed Afroz · Data Analytics Intern · Week 4 End-to-End Case Study
A10: 🔍 KEY FINDINGS
A11: 🏆 BQ1: Electronics is the #1 category
A12: Electronics contributes the highest revenue — driven by Laptop (₹58K unit price), Smart TV, and Smart Watch. Laptops alone appear in 9 orders and generate the single largest product revenue. Fashion follows at #2. Books and Beauty are the lowest contributors.
A15: 🌍 BQ2: South Region is the best performer
A16: South region leads in both order count and total revenue. It dominates Online and Wholesale channels. North is a close #2. Central region is the weakest — very few orders with low revenue. Strategy: replicate South's channel mix and product focus in Central.
A19: 📅 December is the strongest month
A20: Revenue peaks in December (₹94L) driven by festive season demand. Q4 alone contributes ~33% of annual revenue. April is the weakest month. There is a consistent upward growth trend from Jan to Dec — indicating healthy business momentum.
A23: 📊 Q4 dominates quarterly performance
A24: Q4 (Oct–Dec) generates the highest quarterly revenue. QoQ growth accelerates from Q2 onwards. Q1 is the weakest quarter. Action: Pre-stock Electronics from August, launch Diwali campaigns in September, Christmas offers in November.
A27: 📡 Online channel is the revenue leader
A28: Online channel accounts for the majority of revenue at ~56%. Retail Store follows at ~31%. Wholesale is the smallest channel. Online also carries lower average discounts — meaning higher margins. Invest more in digital marketing to grow this channel further.
A31: 💰 Discounts reducing net revenue in Fashion & Beauty
... A35: 📌 STRATEGIC RECOMMENDATIONS
A36: R1 | B36: Expand Electronics SKUs | F36: Launch EMI options on Laptops and Smart TVs to drive more high-value orders
A37: R2 | B37: Invest in South & North | F37: Launch regional exclusive offers and same-day delivery to grow order volume
A38: R3 | B38: Fix April revenue dip | F38: Launch Summer Mega Sale campaign in April focusing on Electronics and Sports
A39: R4 | B39: Grow Online channel | F39: Invest in app UX, SEO and digital ads — target 15% YoY growth in online revenue
A40: R5 | B40: Rationalize discounts | F40: Cap Fashion/Beauty seasonal discounts at 15% and replace rest with loyalty points
A41: R6 | B41: Q4 preparedness | F41: Pre-stock Laptops and Smart TVs from August to handle Diwali and Christmas surge
